app/__init__.py
app/main.py
module_perso/__init__.py
module_perso/affichage.py
module_perso/changement_map.py
module_perso/db_extract.py
module_perso/decorateurs.py
module_perso/fraction.py
module_perso/jeu.py
module_perso/joueur.py
module_perso/logging_config.py
module_perso/pion.py
module_perso/plateau.py
module_perso/websocketo.py
dev_2-2.0.41.dist-info/METADATA
dev_2-2.0.41.dist-info/WHEEL
dev_2-2.0.41.dist-info/entry_points.txt
dev_2-2.0.41.dist-info/top_level.txt
dev_2-2.0.41.dist-info/RECORD
