Metadata-Version: 2.1
Name: dev_2
Version: 2.0.41
Summary: Bibliothèque Python pour des jeux de plateau
Home-page: https://github.com/Ajkll/dev2_jeux_plateau_prod
Author: Alex
Author-email: Alexisjacobs@protonmail.com
Classifier: Programming Language :: Python :: 3
Classifier: License :: OSI Approved :: MIT License
Classifier: Operating System :: OS Independent
Requires-Python: >=3.6
